setup.cfg
setup.py
draftlog/__init__.py
draftlog/ansi.py
draftlog/drafter.py
draftlog/lcs.py
draftlog/loading.py
draftlog/logdraft.py
draftlog.egg-info/PKG-INFO
draftlog.egg-info/SOURCES.txt
draftlog.egg-info/dependency_links.txt
draftlog.egg-info/requires.txt
draftlog.egg-info/top_level.txt