Metadata-Version: 1.0
Name: draftlog
Version: 2.1.9
Summary: Create updatable log lines into the terminal.
Home-page: https://github.com/kepoorhampond/python-draftlog
Author: Kepoor Hampond
Author-email: kepoorh@gmail.com
License: MIT
Platform: UNKNOWN
